aitelier/__init__.py
aitelier/agents/__init__.py
aitelier/agents/_base.py
aitelier/agents/agent.py
aitelier/agents/react.py
aitelier/errors/__init__.py
aitelier/errors/base.py
aitelier/errors/react.py
aitelier/model/__init__.py
aitelier/model/model.py
aitelier/prompt/__init__.py
aitelier/prompt/_base.py
aitelier/prompt/agent.py
aitelier/prompt/react.py
aitelier/tool/__init__.py
aitelier/tool/tool.py
aitelier-0.2.1.dist-info/LICENSE
aitelier-0.2.1.dist-info/METADATA
aitelier-0.2.1.dist-info/WHEEL
aitelier-0.2.1.dist-info/top_level.txt
aitelier-0.2.1.dist-info/RECORD
