Metadata-Version: 2.2
Name: aitelier
Version: 0.2.1
Summary: An atelier for AI Agents.
Maintainer-email: Riccardo Musmeci <riccardomusmeci92@gmail.com>
License-File: LICENSE
Requires-Dist: mlx-llm
Requires-Dist: anthropic
Provides-Extra: dev
Requires-Dist: black==23.3.0; extra == "dev"
Requires-Dist: ruff==0.0.264; extra == "dev"
Requires-Dist: mypy==1.2.0; extra == "dev"
